{"pageProps":{"data":{"conteudo":[{"conteudo":"Aleluia! Louvai a Deus no seu santuário; louvai-o no firmamento, obra do seu poder."},{"conteudo":"Louvai-o pelos seus poderosos feitos; louvai-o consoante a sua muita grandeza."},{"conteudo":"Louvai-o ao som da trombeta; louvai-o com saltério e com harpa."},{"conteudo":"Louvai-o com adufes e danças; louvai-o com instrumentos de cordas e com flautas."},{"conteudo":"Louvai-o com címbalos sonoros; louvai-o com címbalos retumbantes."},{"conteudo":"Todo ser que respira louve ao Senhor. Aleluia!"}],"nomeLivro":[{"livro_nome":"Salmos","livro_abreviado":"sl"}],"quantidadecapitulo":[{"capitulo":150}],"nomeVersao":[{"versao_nome":"1993 - Almeida Revisada e Atualizada"}],"capituloAtual":150}},"__N_SSG":true}